dagster_gcp/__init__.py
dagster_gcp/version.py
dagster_gcp/bigquery/__init__.py
dagster_gcp/bigquery/configs.py
dagster_gcp/bigquery/ops.py
dagster_gcp/bigquery/resources.py
dagster_gcp/bigquery/solids.py
dagster_gcp/bigquery/types.py
dagster_gcp/dataproc/__init__.py
dagster_gcp/dataproc/configs.py
dagster_gcp/dataproc/configs_dataproc_cluster.py
dagster_gcp/dataproc/configs_dataproc_job.py
dagster_gcp/dataproc/ops.py
dagster_gcp/dataproc/resources.py
dagster_gcp/dataproc/solids.py
dagster_gcp/dataproc/types.py
dagster_gcp/dataproc/types_dataproc_cluster.py
dagster_gcp/dataproc/types_dataproc_job.py
dagster_gcp/gcs/__init__.py
dagster_gcp/gcs/compute_log_manager.py
dagster_gcp/gcs/file_manager.py
dagster_gcp/gcs/gcs_fake_resource.py
dagster_gcp/gcs/io_manager.py
dagster_gcp/gcs/resources.py
dagster_gcp-1.0.5.dist-info/LICENSE
dagster_gcp-1.0.5.dist-info/METADATA
dagster_gcp-1.0.5.dist-info/WHEEL
dagster_gcp-1.0.5.dist-info/top_level.txt
dagster_gcp-1.0.5.dist-info/RECORD
